windowblur/__init__.py
windowblur/windowblur.py
windowblur-0.0.2.dist-info/LICENSE
windowblur-0.0.2.dist-info/METADATA
windowblur-0.0.2.dist-info/WHEEL
windowblur-0.0.2.dist-info/top_level.txt
windowblur-0.0.2.dist-info/RECORD
