Metadata-Version: 2.1
Name: windowblur
Version: 0.0.2
Summary: Some simple window blur functions
Author: LIU Dian
Author-email: xgits@outlook.com
License: UNKNOWN
Project-URL: Bug Tracker, https://github.com/pypa/sampleproject/issues
Platform: UNKNOWN
Classifier: Programming Language :: Python :: 2.7
Classifier: Programming Language :: Python :: 3.7
Classifier: License :: OSI Approved :: MIT License
Classifier: Operating System :: Microsoft :: Windows :: Windows 10
Requires-Python: >=2.7
License-File: LICENSE
